[{"nombre":"Isador Guiton","rol":"Administrado","correo":"iguiton0@hao123.com","contrasena":"dD5~5b4,z)"},
{"nombre":"Terrie Shilstone","rol":"SuperAdmin","correo":"tshilstone1@dedecms.com","contrasena":"zW0+&C3Ip4zJr"},
{"nombre":"Darbie Oxton","rol":"Optómetra","correo":"doxton2@behance.net","contrasena":"qO7}SHsjw#FoO0N"},
{"nombre":"Goldy Kembery","rol":"Optómetra","correo":"gkembery3@irs.gov","contrasena":"cI4*mNmPr7"},
{"nombre":"Fredia Bortolozzi","rol":"Optómetra","correo":"fbortolozzi4@free.fr","contrasena":"xH9,oErr4x"},
{"nombre":"Audi Jones","rol":"Optómetra","correo":"ajones5@tripadvisor.com","contrasena":"pH0(vZpe*6q5"},
{"nombre":"Elisha Fairley","rol":"Optómetra","correo":"efairley6@reuters.com","contrasena":"rJ7'Bo\\!ei"},
{"nombre":"Devina Boyat","rol":"Administrador","correo":"dboyat7@ebay.co.uk","contrasena":"mG5(3C9SK8455E"},
{"nombre":"Walliw Geck","rol":"Optómetra","correo":"wgeck8@prlog.org","contrasena":"jK0._KWb\\"},
{"nombre":"Joceline Crowden","rol":"Optómetra","correo":"jcrowden9@hugedomains.com","contrasena":"oE2)x4%Xa>c=zW_$"}]